{
  "name": "BOLLARD LIGHTS",
  "slug": "bollard-lights",
  "url": "https://zionledusa.com/product-category/outdoor/bollard-lights/",
  "sku": "",
  "price": "",
  "description": "",
  "short_desc": "",
  "images": [
    {
      "original": "images\\products\\2-3-300x300.png",
      "webp": "images_optimized\\products\\2-3-300x300.webp",
      "url": "https://zionledusa.com/wp-content/uploads/2025/05/2-3-300x300.png",
      "filename": "2-3-300x300.png",
      "alt": "24W Led Bollard Light AC 120~277V 3CCT"
    }
  ],
  "categories": [],
  "attributes": {},
  "meta_title": "BOLLARD LIGHTS",
  "meta_desc": "",
  "scraped_at": "2026-03-26T21:24:19.142162"
}